isvirtual/VERSION.md
isvirtual/__init__.py
isvirtual/cli.py
isvirtual/main.py
isvirtual-1.4.0.dist-info/METADATA
isvirtual-1.4.0.dist-info/WHEEL
isvirtual-1.4.0.dist-info/entry_points.txt
isvirtual-1.4.0.dist-info/licenses/LICENSE
isvirtual-1.4.0.dist-info/RECORD
