Metadata-Version: 2.3
Name: isvirtual
Version: 1.4.0
Summary: Tool to detect if the current directory is linked to a virtual environment, get the config of this env and more. Work with venv, virtualenv, pipenv, poetry and soon hatch and pdm.
Project-URL: Homepage, https://github.com/AlexMili/isVirtual
Project-URL: Issues, https://github.com/AlexMili/isVirtual/issues
Project-URL: Repository, https://github.com/AlexMili/isVirtual
Project-URL: Documentation, https://github.com/AlexMili/isVirtual
Author: Alex Mili
License: MIT License
License-File: LICENSE
Keywords: env,environment,hatch,pdm,pipenv,poetry,venv,virtual,virtualenv
Classifier: Intended Audience :: Developers
Classifier: License :: OSI Approved :: MIT License
Classifier: Programming Language :: Python
Classifier: Programming Language :: Python :: 3
Classifier: Programming Language :: Python :: 3.3
Classifier: Programming Language :: Python :: 3.4
Classifier: Programming Language :: Python :: 3.5
Classifier: Programming Language :: Python :: 3.6
Classifier: Programming Language :: Python :: 3.7
Classifier: Programming Language :: Python :: 3.8
Classifier: Programming Language :: Python :: 3.10
Classifier: Programming Language :: Python :: 3.11
Classifier: Programming Language :: Python :: 3.12
Classifier: Programming Language :: Python :: 3.13
Requires-Python: >=3.3
Requires-Dist: platformdirs
Requires-Dist: sty
Requires-Dist: typer
